cloudflare_ddns/__init__.py
cloudflare_ddns/__main__.py
cloudflare_ddns/cloudflare.py
cloudflare_ddns/exceptions.py
cloudflare_ddns-1.4.0.dist-info/LICENSE
cloudflare_ddns-1.4.0.dist-info/METADATA
cloudflare_ddns-1.4.0.dist-info/WHEEL
cloudflare_ddns-1.4.0.dist-info/entry_points.txt
cloudflare_ddns-1.4.0.dist-info/top_level.txt
cloudflare_ddns-1.4.0.dist-info/RECORD
