Metadata-Version: 2.1
Name: cloudflare-ddns
Version: 1.4.0
Summary: DDNS script to sync public IP address to CloudFlare dns records
Home-page: https://github.com/ailionx/cloudflare-ddns
Author: Shawn Lin
Author-email: ailionxy@gmail.com
License: MIT
Keywords: cloudflare ddns
Platform: UNKNOWN
Classifier: Development Status :: 5 - Production/Stable
Classifier: Intended Audience :: Developers
Classifier: License :: OSI Approved :: MIT License
Classifier: Topic :: Software Development :: Libraries :: Python Modules
Classifier: Programming Language :: Python :: 3
Requires-Dist: requests
